blueair/__init__.py
blueair/__main__.py
blueair/blueair.py
blueair/cli.py
blueair/database.py
blueair-1.0.0.dist-info/LICENSE.txt
blueair-1.0.0.dist-info/METADATA
blueair-1.0.0.dist-info/WHEEL
blueair-1.0.0.dist-info/entry_points.txt
blueair-1.0.0.dist-info/top_level.txt
blueair-1.0.0.dist-info/RECORD
